aiobtclientrpc/__init__.py
aiobtclientrpc/_base.py
aiobtclientrpc/_deluge.py
aiobtclientrpc/_errors.py
aiobtclientrpc/_qbittorrent.py
aiobtclientrpc/_rtorrent.py
aiobtclientrpc/_transmission.py
aiobtclientrpc/_utils.py
docs/conf.py
tests/__init__.py
tests/base_test.py
tests/common.py
tests/deluge_test.py
tests/errors_test.py
tests/qbittorrent_test.py
tests/rtorrent_test.py
tests/transmission_test.py
tests/utils_test.py
tests/integration_tests/__init__.py
tests/integration_tests/common.py
tests/integration_tests/conftest.py
tests/integration_tests/integration_test.py
tests/integration_tests/proxyserver.py
tests/integration_tests/apis/base.py
tests/integration_tests/apis/deluge.py
tests/integration_tests/apis/qbittorrent.py
tests/integration_tests/apis/rtorrent.py
tests/integration_tests/apis/transmission.py
tests/integration_tests/servers/_rtorrent_common.py
tests/integration_tests/servers/deluge.py
tests/integration_tests/servers/qbittorrent.py
tests/integration_tests/servers/rtorrent_http.py
tests/integration_tests/servers/rtorrent_scgi.py
tests/integration_tests/servers/rtorrent_socket.py
tests/integration_tests/servers/transmission.py
aiobtclientrpc-5.0.1.dist-info/LICENSE
aiobtclientrpc-5.0.1.dist-info/METADATA
aiobtclientrpc-5.0.1.dist-info/WHEEL
aiobtclientrpc-5.0.1.dist-info/top_level.txt
aiobtclientrpc-5.0.1.dist-info/RECORD
