Metadata-Version: 2.1
Name: aiobtclientrpc
Version: 5.0.1
Author-email: plotski <plotski@example.org>
License: GPL-3.0-or-later
Project-URL: Repository, https://codeberg.org/plotski/aiobtclientrpc
Project-URL: Documentation, https://aiobtclientrpc.readthedocs.io
Project-URL: Bug Tracker, https://codeberg.org/plotski/aiobtclientrpc/issues
Project-URL: Changelog, https://codeberg.org/plotski/aiobtclientrpc/raw/branch/master/NEWS
Classifier: Programming Language :: Python :: 3.8
Classifier: Programming Language :: Python :: 3.9
Classifier: Programming Language :: Python :: 3.10
Classifier: Programming Language :: Python :: 3.11
Classifier: License :: OSI Approved :: GNU General Public License v3 or later (GPLv3+)
Requires-Python: >=3.8
License-File: LICENSE
Requires-Dist: async-timeout ==4.*
Requires-Dist: httpx ==0.*
Requires-Dist: httpx-socks ==0.*
Requires-Dist: python-socks[asyncio] ==2.*
Requires-Dist: rencode ==1.0.*
Provides-Extra: dev
Requires-Dist: pytest ; extra == 'dev'
Requires-Dist: pytest-asyncio ; extra == 'dev'
Requires-Dist: pytest-mock ; extra == 'dev'
Requires-Dist: proxy.py ; extra == 'dev'
Requires-Dist: tox ; extra == 'dev'
Requires-Dist: coverage ; extra == 'dev'
Requires-Dist: pytest-cov ; extra == 'dev'
Requires-Dist: ruff ; extra == 'dev'
